{
    "id": 3,
    "title": "Жіноча збірна України провела навчально-тренувальний збір в Ужгороді",
    "excerpt": "З 2 по 11 червня жіноча збірна України з дзюдо у складі 28 спортсменок проводила навчально-тренувальний збір в Ужгороді під керівництвом досвідчених тренерів.",
    "content": "<p>З 2 по 11 червня жіноча збірна України з дзюдо у складі 28 спортсменок проводила навчально-тренувальний збір в Ужгороді.</p><h3>Тренерський склад:</h3><p>Під керівництвом досвідчених тренерів дівчата працювали над різними аспектами підготовки:</p><ul><li><strong>Ганна Каштанова</strong> — головний тренер</li><li><strong>Дмитро Бондарчук</strong> — тренер збірної</li><li><strong>Андрій Блошенко</strong> — тренер збірної</li><li><strong>Андрій Бурдун</strong> — тренер збірної</li></ul><h3>Програма збору:</h3><p>Спортсменки працювали над комплексною підготовкою:</p><ul><li>Загальнофізична підготовка</li><li>Відпрацювання змагальних елементів</li><li>Два повноцінні дні боротьби</li><li>Технічна та тактична підготовка</li></ul><h3>Майстер-клас від Антона Савицького:</h3><p>В один із тренувальних днів майстер-клас та інтенсивне тренування для спортсменок провів <strong>лідер чоловічої збірної України з дзюдо, переможець і призер турнірів IJF World Tour Антон Савицький</strong>.</p><p>Антон поділився своїм досвідом, продемонстрував технічні прийоми та тактичні нюанси, які допоможуть дівчатам ефективніше вести боротьбу на татамі.</p><h3>Найближчі змагання:</h3><p>Відзначимо, що найближчим стартом в національному календарі змагань стане <strong>Кубок України з дзюдо, який відбудеться 15 липня</strong>.</p><p>Навчально-тренувальний збір в Ужгороді став важливим етапом підготовки жіночої збірної до майбутніх змагань та продемонстрував високий рівень організації тренувального процесу.</p>",
    "category": "events",
    "publishedAt": "2025-06-12T09:00:00Z",
    "updatedAt": "2025-06-12T09:00:00Z",
    "author": {
        "name": "Пресс-служба ФДУ",
        "email": "press@fju.org.ua",
        "avatar": "assets/authors/fju-press.jpg"
    },
    "image": {
        "url": "assets/news/photo_2025-06-10_16-01-11.jpg",
        "alt": "Жіноча збірна України на навчально-тренувальному зборі в Ужгороді",
        "caption": "Спортсменки жіночої збірної України під час тренувального збору"
    },
    "featured": false,
    "tags": ["жіноча збірна", "тренувальний збір", "Ужгород", "підготовка", "Антон Савицький"],
    "stats": {
        "views": 1180,
        "likes": 95,
        "shares": 28
    },
    "seo": {
        "metaTitle": "Жіноча збірна України провела тренувальний збір в Ужгороді",
        "metaDescription": "28 спортсменок жіночої збірної України з дзюдо провели навчально-тренувальний збір в Ужгороді з 2 по 11 червня",
        "keywords": ["жіноча збірна", "дзюдо", "тренувальний збір", "Ужгород", "підготовка", "Антон Савицький"]
    },
    "related": [1, 2, 4],
    "status": "published",
    "language": "uk"
} 